{"nodes": [{"name": "GSO"}, {"name": "LGA"}, {"name": "EWR"}, {"name": "DTW"}, {"name": "ATL"}, {"name": "ORD"}, {"name": "DEN"}, {"name": "LGA"}, {"name": "EWR"}, {"name": "ORD"}, {"name": "DEN"}, {"name": "DTW"}, {"name": "ATL"}], "links": [{"source": 1, "target": 0, "value": 17.977011494252874}, {"source": 2, "target": 0, "value": 13.707317073170731}, {"source": 3, "target": 0, "value": 5.443037974683544}, {"source": 4, "target": 0, "value": 5.159817351598173}, {"source": 5, "target": 0, "value": 1.5689655172413792}, {"source": 6, "target": 0, "value": -6.615384615384615}, {"source": 0, "target": 7, "value": 22.470588235294116}, {"source": 0, "target": 8, "value": 15.439024390243903}, {"source": 0, "target": 9, "value": 4.385964912280702}, {"source": 0, "target": 10, "value": 4.0}, {"source": 0, "target": 11, "value": 2.9746835443037973}, {"source": 0, "target": 12, "value": 1.1050228310502284}]}